{"nodes": [{"id": "t5_2qk6v", "name": "retrogaming", "interactions": 32114, "users": 1723, "degree": 7, "strength": 393}, {"id": "t5_2s0qt", "name": "Gameboy", "interactions": 18795, "users": 1490, "degree": 3, "strength": 147}, {"id": "t5_2qhhw", "name": "PS3", "interactions": 15531, "users": 1243, "degree": 3, "strength": 117}, {"id": "t5_2s9jx", "name": "ps3homebrew", "interactions": 2822, "users": 272, "degree": 1, "strength": 43}, {"id": "t5_2rww7", "name": "originalxbox", "interactions": 8944, "users": 653, "degree": 1, "strength": 27}, {"id": "t5_3c23m", "name": "crtgaming", "interactions": 18155, "users": 1355, "degree": 4, "strength": 160}, {"id": "t5_2ruhy", "name": "3DS", "interactions": 21708, "users": 1656, "degree": 4, "strength": 141}, {"id": "t5_2s8fe", "name": "gamecollecting", "interactions": 35393, "users": 2393, "degree": 10, "strength": 568}, {"id": "t5_2sbwh", "name": "Gamecube", "interactions": 10927, "users": 825, "degree": 1, "strength": 59}, {"id": "t5_2tjv1", "name": "consolerepair", "interactions": 7976, "users": 740, "degree": 1, "strength": 39}, {"id": "t5_2sjnz", "name": "wiiu", "interactions": 5409, "users": 383, "degree": 1, "strength": 33}, {"id": "t5_3eeaa", "name": "3dspiracy", "interactions": 4336, "users": 429, "degree": 1, "strength": 43}, {"id": "t5_2r8uk", "name": "ps2", "interactions": 12724, "users": 828, "degree": 2, "strength": 61}, {"id": "t5_2sayt", "name": "psx", "interactions": 6038, "users": 375, "degree": 1, "strength": 28}, {"id": "t5_2r529", "name": "nes", "interactions": 4452, "users": 279, "degree": 1, "strength": 33}, {"id": "t5_2rany", "name": "snes", "interactions": 7153, "users": 448, "degree": 1, "strength": 35}, {"id": "t5_3jnmz", "name": "NSCollectors", "interactions": 4977, "users": 431, "degree": 1, "strength": 51}, {"id": "t5_2s34r", "name": "n64", "interactions": 12271, "users": 846, "degree": 1, "strength": 49}], "edges": [{"source": "t5_2qk6v", "target": "t5_2s0qt", "shared_users": 49, "cosine": 0.03058160729211997, "jaccard": 0.015486725663716814}, {"source": "t5_2qk6v", "target": "t5_2s8fe", "shared_users": 90, "cosine": 0.04432293606036753, "jaccard": 0.022354694485842028}, {"source": "t5_2qk6v", "target": "t5_3c23m", "shared_users": 60, "cosine": 0.039268016431819666, "jaccard": 0.019880715705765408}, {"source": "t5_2qk6v", "target": "t5_2r529", "shared_users": 33, "cosine": 0.04759586231358901, "jaccard": 0.01675977653631285}, {"source": "t5_2qk6v", "target": "t5_2rany", "shared_users": 35, "cosine": 0.03983697917815339, "jaccard": 0.01638576779026217}, {"source": "t5_2s0qt", "target": "t5_2s8fe", "shared_users": 59, "cosine": 0.031245503551066974, "jaccard": 0.01542887029288703}, {"source": "t5_2s0qt", "target": "t5_2tjv1", "shared_users": 39, "cosine": 0.037141172774122044, "jaccard": 0.017800091282519397}, {"source": "t5_2qhhw", "target": "t5_2s9jx", "shared_users": 43, "cosine": 0.07395174720885915, "jaccard": 0.029211956521739132}, {"source": "t5_2qhhw", "target": "t5_2s8fe", "shared_users": 35, "cosine": 0.02029369508301516, "jaccard": 0.009719522354901417}, {"source": "t5_2rww7", "target": "t5_3c23m", "shared_users": 27, "cosine": 0.028703676445024324, "jaccard": 0.013629480060575468}, {"source": "t5_3c23m", "target": "t5_2s8fe", "shared_users": 40, "cosine": 0.022213602411611726, "jaccard": 0.010787486515641856}, {"source": "t5_3c23m", "target": "t5_2r8uk", "shared_users": 33, "cosine": 0.031155098157188022, "jaccard": 0.015348837209302326}, {"source": "t5_2ruhy", "target": "t5_2s8fe", "shared_users": 33, "cosine": 0.01657724760552091, "jaccard": 0.008217131474103585}, {"source": "t5_2ruhy", "target": "t5_2sjnz", "shared_users": 33, "cosine": 0.04143662611055636, "jaccard": 0.016450648055832504}, {"source": "t5_2ruhy", "target": "t5_3eeaa", "shared_users": 43, "cosine": 0.051016380515790716, "jaccard": 0.021057786483839373}, {"source": "t5_2s8fe", "target": "t5_2sbwh", "shared_users": 59, "cosine": 0.041990755451834526, "jaccard": 0.01867679645457423}, {"source": "t5_2s8fe", "target": "t5_3jnmz", "shared_users": 51, "cosine": 0.0502180901180394, "jaccard": 0.01839163360980887}, {"source": "t5_2s8fe", "target": "t5_2s34r", "shared_users": 49, "cosine": 0.034438129055664346, "jaccard": 0.015360501567398118}, {"source": "t5_2r8uk", "target": "t5_2sayt", "shared_users": 28, "cosine": 0.050248977525428784, "jaccard": 0.023829787234042554}]}