{"nodes": [{"id": "t5_331ct", "name": "fivenightsatfreddys", "interactions": 47831, "users": 2535, "degree": 6, "strength": 425}, {"id": "t5_36f29", "name": "fnaftheories", "interactions": 16431, "users": 440, "degree": 1, "strength": 208}, {"id": "t5_3j1q3", "name": "BendyAndTheInkMachine", "interactions": 9287, "users": 402, "degree": 1, "strength": 24}, {"id": "t5_2hp62i", "name": "fnafmeme", "interactions": 15757, "users": 404, "degree": 1, "strength": 74}, {"id": "t5_564ka6", "name": "PoppyPlaytime", "interactions": 11675, "users": 591, "degree": 1, "strength": 20}], "edges": [{"source": "t5_331ct", "target": "t5_36f29", "shared_users": 208, "cosine": 0.19694638556693236, "jaccard": 0.0751716660643296}, {"source": "t5_331ct", "target": "t5_3j1q3", "shared_users": 24, "cosine": 0.023774381824192486, "jaccard": 0.008238928939237899}, {"source": "t5_331ct", "target": "t5_2hp62i", "shared_users": 74, "cosine": 0.0731226724420469, "jaccard": 0.02582897033158813}, {"source": "t5_331ct", "target": "t5_564ka6", "shared_users": 20, "cosine": 0.01633982020197862, "jaccard": 0.00643915003219575}]}