{"nodes": [{"id": "t5_2vae5", "name": "HairStyleAdvice", "interactions": 17401, "users": 789, "degree": 1, "strength": 77}, {"id": "t5_2wn4a", "name": "HairDye", "interactions": 78232, "users": 5679, "degree": 20, "strength": 1713}, {"id": "t5_2qhta", "name": "cats", "interactions": 331736, "users": 26842, "degree": 63, "strength": 8223}, {"id": "t5_2um28", "name": "makeuptips", "interactions": 45590, "users": 3008, "degree": 7, "strength": 554}, {"id": "t5_2rl0h", "name": "ARTIST", "interactions": 76362, "users": 5124, "degree": 17, "strength": 1669}, {"id": "t5_2st00", "name": "goldenretrievers", "interactions": 37492, "users": 2926, "degree": 5, "strength": 226}, {"id": "t5_2rww2", "name": "MakeupAddiction", "interactions": 66656, "users": 4724, "degree": 13, "strength": 849}, {"id": "t5_367ex", "name": "DogAdvice", "interactions": 67076, "users": 5014, "degree": 9, "strength": 611}, {"id": "t5_2rgjh", "name": "amiugly", "interactions": 102275, "users": 8143, "degree": 18, "strength": 2455}, {"id": "t5_2rf5w", "name": "drawme", "interactions": 31315, "users": 2257, "degree": 2, "strength": 65}, {"id": "t5_2vy7f", "name": "redditgetsdrawnbadly", "interactions": 13922, "users": 1102, "degree": 2, "strength": 59}, {"id": "t5_3bt1s", "name": "amIuglyBrutallyHonest", "interactions": 73962, "users": 6244, "degree": 13, "strength": 2064}, {"id": "t5_3l18i", "name": "LooksmaxingAdvice", "interactions": 32451, "users": 3070, "degree": 5, "strength": 461}, {"id": "t5_2qjof", "name": "pitbulls", "interactions": 47756, "users": 2773, "degree": 6, "strength": 396}, {"id": "t5_2sgc2", "name": "AbstractArt", "interactions": 50718, "users": 2643, "degree": 8, "strength": 618}, {"id": "t5_prg6z", "name": "FridgeDetective", "interactions": 175712, "users": 9811, "degree": 25, "strength": 3115}, {"id": "t5_2w0u7", "name": "AsianBeauty", "interactions": 21358, "users": 1906, "degree": 4, "strength": 227}, {"id": "t5_2qlac", "name": "beauty", "interactions": 48406, "users": 2883, "degree": 8, "strength": 498}, {"id": "t5_2qrwc", "name": "Makeup", "interactions": 20130, "users": 1178, "degree": 4, "strength": 216}, {"id": "t5_2ihy50", "name": "DermatologyQuestions", "interactions": 33451, "users": 3255, "degree": 2, "strength": 199}, {"id": "t5_2tbbg", "name": "SkincareAddiction", "interactions": 63768, "users": 6639, "degree": 14, "strength": 1085}, {"id": "t5_2qhhk", "name": "dogs", "interactions": 34927, "users": 2064, "degree": 4, "strength": 276}, {"id": "t5_2st2l", "name": "FunnyAnimals", "interactions": 35696, "users": 1715, "degree": 4, "strength": 371}, {"id": "t5_5u5d30", "name": "trueratediscussions", "interactions": 82018, "users": 2689, "degree": 7, "strength": 450}, {"id": "t5_2s1th", "name": "Doppleganger", "interactions": 52264, "users": 3046, "degree": 4, "strength": 359}, {"id": "t5_7bc4vn", "name": "Howtolooksmax", "interactions": 103108, "users": 7243, "degree": 19, "strength": 2138}, {"id": "t5_3cbed", "name": "NameMyDog", "interactions": 121700, "users": 8226, "degree": 17, "strength": 3975}, {"id": "t5_28jabm", "name": "fragranceclones", "interactions": 44244, "users": 3134, "degree": 3, "strength": 749}, {"id": "t5_2vbb3", "name": "Colognes", "interactions": 72848, "users": 5536, "degree": 7, "strength": 1651}, {"id": "t5_2rkzz", "name": "Noses", "interactions": 66449, "users": 3620, "degree": 7, "strength": 686}, {"id": "t5_319c0", "name": "IDmydog", "interactions": 23767, "users": 1680, "degree": 3, "strength": 225}, {"id": "t5_29c8x5", "name": "VoidCats", "interactions": 9394, "users": 491, "degree": 1, "strength": 64}, {"id": "t5_2twpw", "name": "blackcats", "interactions": 54748, "users": 3385, "degree": 4, "strength": 567}, {"id": "t5_2sn56", "name": "CatAdvice", "interactions": 83208, "users": 6421, "degree": 10, "strength": 1259}, {"id": "t5_7bx0f3", "name": "DarkArtwork", "interactions": 20861, "users": 1016, "degree": 3, "strength": 141}, {"id": "t5_26594g", "name": "acrylicpainting", "interactions": 9811, "users": 587, "degree": 1, "strength": 83}, {"id": "t5_2qirl", "name": "painting", "interactions": 42426, "users": 2478, "degree": 7, "strength": 533}, {"id": "t5_37xo2", "name": "RoastMe", "interactions": 287525, "users": 17206, "degree": 47, "strength": 5230}, {"id": "t5_2qh7a", "name": "Art", "interactions": 12230, "users": 950, "degree": 2, "strength": 123}, {"id": "t5_2qvp9", "name": "drawing", "interactions": 41645, "users": 2339, "degree": 7, "strength": 479}, {"id": "t5_2rwal", "name": "DigitalArt", "interactions": 16397, "users": 1424, "degree": 4, "strength": 185}, {"id": "t5_2sda0", "name": "fragrance", "interactions": 72782, "users": 5550, "degree": 7, "strength": 1855}, {"id": "t5_2vmr7", "name": "fragranceswap", "interactions": 27345, "users": 1512, "degree": 2, "strength": 302}, {"id": "t5_2ygor", "name": "AmericanBully", "interactions": 11504, "users": 733, "degree": 1, "strength": 51}, {"id": "t5_2qh1o", "name": "aww", "interactions": 81597, "users": 4234, "degree": 7, "strength": 926}, {"id": "t5_2s427", "name": "Eyebleach", "interactions": 22153, "users": 607, "degree": 1, "strength": 33}, {"id": "t5_3h7cm", "name": "Straycats", "interactions": 10493, "users": 420, "degree": 1, "strength": 36}, {"id": "t5_2suml", "name": "Awww", "interactions": 41941, "users": 1892, "degree": 7, "strength": 481}, {"id": "t5_snj8v", "name": "animalsdoingstuff", "interactions": 15271, "users": 595, "degree": 1, "strength": 48}, {"id": "t5_3n328", "name": "Catswithjobs", "interactions": 13768, "users": 613, "degree": 1, "strength": 52}, {"id": "t5_30sy6", "name": "seniordogs", "interactions": 22674, "users": 1124, "degree": 4, "strength": 245}, {"id": "t5_3epk9", "name": "OldManDog", "interactions": 15144, "users": 698, "degree": 1, "strength": 110}, {"id": "t5_2qkya", "name": "PlasticSurgery", "interactions": 42166, "users": 4213, "degree": 7, "strength": 394}, {"id": "t5_2uols", "name": "Sephora", "interactions": 28807, "users": 2439, "degree": 6, "strength": 405}, {"id": "t5_ruinb", "name": "GlowUps", "interactions": 38967, "users": 1313, "degree": 2, "strength": 96}, {"id": "t5_3g77o3", "name": "standardissuecat", "interactions": 12533, "users": 654, "degree": 1, "strength": 59}, {"id": "t5_6s73fd", "name": "FaceRatings", "interactions": 35674, "users": 1993, "degree": 5, "strength": 494}, {"id": "t5_3lfiq", "name": "badfoodporn", "interactions": 33623, "users": 822, "degree": 1, "strength": 57}, {"id": "t5_379gw", "name": "30PlusSkinCare", "interactions": 48553, "users": 4030, "degree": 11, "strength": 700}, {"id": "t5_2qmsf", "name": "Hair", "interactions": 39448, "users": 3444, "degree": 9, "strength": 610}, {"id": "t5_3hjjf", "name": "NameMyCat", "interactions": 187058, "users": 14585, "degree": 32, "strength": 7668}, {"id": "t5_2rn7d", "name": "Catnames", "interactions": 103775, "users": 7609, "degree": 13, "strength": 4442}, {"id": "t5_2ryza", "name": "CATHELP", "interactions": 58764, "users": 4135, "degree": 5, "strength": 687}, {"id": "t5_2scm4", "name": "40something", "interactions": 69821, "users": 4097, "degree": 9, "strength": 721}, {"id": "t5_2w2f5", "name": "selfie", "interactions": 58490, "users": 3105, "degree": 11, "strength": 744}, {"id": "t5_31f0i", "name": "KoreanBeauty", "interactions": 4163, "users": 429, "degree": 1, "strength": 40}, {"id": "t5_2r2ct", "name": "Chihuahua", "interactions": 29842, "users": 1959, "degree": 2, "strength": 86}, {"id": "t5_2qn3z", "name": "kittens", "interactions": 14964, "users": 711, "degree": 2, "strength": 95}, {"id": "t5_2rw7o", "name": "puppy101", "interactions": 31797, "users": 2608, "degree": 5, "strength": 291}, {"id": "t5_2zw8v", "name": "OpenDogTraining", "interactions": 13614, "users": 844, "degree": 2, "strength": 83}, {"id": "t5_2qoqt", "name": "Faces", "interactions": 26736, "users": 1512, "degree": 5, "strength": 334}, {"id": "t5_2re83", "name": "amihot", "interactions": 46871, "users": 1553, "degree": 3, "strength": 113}, {"id": "t5_2y0nv", "name": "bathandbodyworks", "interactions": 68061, "users": 3828, "degree": 6, "strength": 349}, {"id": "t5_30vvl", "name": "Ulta", "interactions": 16995, "users": 1515, "degree": 2, "strength": 176}, {"id": "t5_2sgxv", "name": "femalehairadvice", "interactions": 8946, "users": 716, "degree": 1, "strength": 36}, {"id": "t5_2ub51", "name": "learntodraw", "interactions": 29883, "users": 1831, "degree": 3, "strength": 194}, {"id": "t5_31nsz", "name": "tretinoin", "interactions": 16306, "users": 1438, "degree": 2, "strength": 136}, {"id": "t5_2wp5v", "name": "orangecats", "interactions": 25351, "users": 1524, "degree": 4, "strength": 360}, {"id": "t5_7j5zwe", "name": "whatismycookiecutter", "interactions": 41953, "users": 2060, "degree": 3, "strength": 143}, {"id": "t5_2s6zw", "name": "doppelganger", "interactions": 20968, "users": 1131, "degree": 2, "strength": 165}, {"id": "t5_2vgxd", "name": "ragdolls", "interactions": 13270, "users": 1165, "degree": 1, "strength": 79}, {"id": "t5_2s8y4", "name": "Perfumes", "interactions": 47074, "users": 3494, "degree": 4, "strength": 1113}, {"id": "t5_31m29", "name": "seniorkitties", "interactions": 26134, "users": 1252, "degree": 3, "strength": 249}, {"id": "t5_2vz7o", "name": "uglyduckling", "interactions": 36727, "users": 1728, "degree": 5, "strength": 337}, {"id": "t5_2xwgx", "name": "MakeupAddicts", "interactions": 9114, "users": 412, "degree": 1, "strength": 42}, {"id": "t5_2swg6", "name": "oilpainting", "interactions": 9329, "users": 883, "degree": 1, "strength": 114}, {"id": "t5_32xps", "name": "orthotropics", "interactions": 7395, "users": 623, "degree": 2, "strength": 141}, {"id": "t5_qp633", "name": "Mewing", "interactions": 6156, "users": 633, "degree": 1, "strength": 96}, {"id": "t5_3jayp", "name": "BeautyGuruChatter", "interactions": 13319, "users": 904, "degree": 2, "strength": 78}, {"id": "t5_3x4r2p", "name": "45PlusSkincare", "interactions": 8984, "users": 516, "degree": 1, "strength": 45}, {"id": "t5_2qoaq", "name": "ArtCrit", "interactions": 15387, "users": 1033, "degree": 2, "strength": 90}, {"id": "t5_32v6c", "name": "Artadvice", "interactions": 11536, "users": 839, "degree": 1, "strength": 41}, {"id": "t5_2taso", "name": "labrador", "interactions": 28039, "users": 2013, "degree": 3, "strength": 130}, {"id": "t5_458lb9", "name": "VindictaRateCelebs", "interactions": 32827, "users": 1947, "degree": 5, "strength": 267}, {"id": "t5_6r2wpv", "name": "MakeMeFeelGood", "interactions": 10902, "users": 582, "degree": 1, "strength": 51}, {"id": "t5_9jxvcg", "name": "ShareYourSelfie", "interactions": 11233, "users": 553, "degree": 2, "strength": 99}, {"id": "t5_2y5wf", "name": "CalicoKittys", "interactions": 9188, "users": 528, "degree": 1, "strength": 58}, {"id": "t5_37fyau", "name": "trueratecelebrities", "interactions": 4822, "users": 307, "degree": 1, "strength": 51}, {"id": "t5_71gtbx", "name": "SelfieOver25", "interactions": 19827, "users": 784, "degree": 1, "strength": 123}, {"id": "t5_3n22p", "name": "Catculations", "interactions": 18923, "users": 640, "degree": 2, "strength": 60}, {"id": "t5_3oxw9d", "name": "tummytucksurgery", "interactions": 16997, "users": 1130, "degree": 1, "strength": 61}, {"id": "t5_2qse3", "name": "acne", "interactions": 9942, "users": 1147, "degree": 2, "strength": 112}, {"id": "t5_2ui5x", "name": "Accutane", "interactions": 15650, "users": 1682, "degree": 2, "strength": 72}, {"id": "t5_2qnh3", "name": "RATS", "interactions": 33589, "users": 2418, "degree": 4, "strength": 123}, {"id": "t5_3noa4", "name": "truerateme", "interactions": 10181, "users": 801, "degree": 2, "strength": 95}, {"id": "t5_39em5", "name": "toastme", "interactions": 42127, "users": 2168, "degree": 4, "strength": 314}, {"id": "t5_2wnt6", "name": "TabbyCats", "interactions": 7845, "users": 423, "degree": 1, "strength": 35}, {"id": "t5_2qm5g", "name": "puppies", "interactions": 10505, "users": 582, "degree": 1, "strength": 46}, {"id": "t5_3afrc", "name": "boopthesnoot", "interactions": 45600, "users": 1082, "degree": 4, "strength": 275}, {"id": "t5_2re84", "name": "Rateme", "interactions": 38654, "users": 2698, "degree": 7, "strength": 681}, {"id": "t5_35s40", "name": "coloranalysis", "interactions": 23057, "users": 1764, "degree": 3, "strength": 112}, {"id": "t5_2tqbr", "name": "LushCosmetics", "interactions": 25280, "users": 2255, "degree": 1, "strength": 62}, {"id": "t5_3yqdrv", "name": "FemFragLab", "interactions": 56071, "users": 3933, "degree": 8, "strength": 1502}, {"id": "t5_2sgkq", "name": "PetMice", "interactions": 6580, "users": 470, "degree": 1, "strength": 30}, {"id": "t5_cqsr2u", "name": "colognecheck", "interactions": 4895, "users": 416, "degree": 1, "strength": 96}, {"id": "t5_2qh79", "name": "Illustration", "interactions": 8905, "users": 563, "degree": 2, "strength": 124}, {"id": "t5_2w8pb", "name": "Indiemakeupandmore", "interactions": 12196, "users": 783, "degree": 1, "strength": 55}, {"id": "t5_2qncz", "name": "sketches", "interactions": 10645, "users": 577, "degree": 1, "strength": 92}, {"id": "t5_2r5qg", "name": "dogpictures", "interactions": 29273, "users": 1566, "degree": 3, "strength": 139}, {"id": "t5_3ccek", "name": "RoastMyCat", "interactions": 25393, "users": 1105, "degree": 1, "strength": 88}, {"id": "t5_2qnaq", "name": "Artists", "interactions": 9792, "users": 489, "degree": 1, "strength": 36}, {"id": "t5_2sx1m", "name": "AskVet", "interactions": 28842, "users": 1966, "degree": 4, "strength": 321}, {"id": "t5_2qiy5", "name": "DOG", "interactions": 24780, "users": 1363, "degree": 2, "strength": 72}, {"id": "t5_2td8l", "name": "Watercolor", "interactions": 17903, "users": 1194, "degree": 2, "strength": 161}, {"id": "t5_2uobx", "name": "catfood", "interactions": 8007, "users": 544, "degree": 1, "strength": 59}, {"id": "t5_5erdvw", "name": "koreanskincare", "interactions": 4703, "users": 491, "degree": 1, "strength": 71}, {"id": "t5_2t5r0", "name": "VictoriasSecret", "interactions": 3945, "users": 487, "degree": 1, "strength": 40}, {"id": "t5_22m7gw", "name": "Kibbe", "interactions": 7392, "users": 457, "degree": 1, "strength": 33}, {"id": "t5_2vxds", "name": "FreckledGirls", "interactions": 11950, "users": 433, "degree": 1, "strength": 32}, {"id": "t5_2xf3z", "name": "lynxpointsiamese", "interactions": 4380, "users": 337, "degree": 1, "strength": 30}, {"id": "t5_2sic2", "name": "catcare", "interactions": 4688, "users": 420, "degree": 1, "strength": 35}, {"id": "t5_3fwbd", "name": "Skincare_Addiction", "interactions": 23365, "users": 1559, "degree": 3, "strength": 243}, {"id": "t5_8mnmsd", "name": "selfieover40", "interactions": 21958, "users": 1144, "degree": 1, "strength": 223}, {"id": "t5_2vzhu", "name": "ProCreate", "interactions": 11621, "users": 972, "degree": 1, "strength": 56}, {"id": "t5_23e19j", "name": "IllegallySmolCats", "interactions": 11416, "users": 460, "degree": 1, "strength": 40}, {"id": "t5_2qh6o", "name": "Pets", "interactions": 27208, "users": 1362, "degree": 2, "strength": 100}, {"id": "t5_2tt9j", "name": "torties", "interactions": 21138, "users": 1429, "degree": 2, "strength": 157}, {"id": "t5_2v6m5", "name": "SeniorCats", "interactions": 6581, "users": 321, "degree": 1, "strength": 58}, {"id": "t5_af2s43", "name": "ScentHeads", "interactions": 15313, "users": 1017, "degree": 1, "strength": 329}, {"id": "t5_7l5bxn", "name": "CatDistributionSystem", "interactions": 26846, "users": 1077, "degree": 2, "strength": 169}, {"id": "t5_v051u", "name": "velvethippos", "interactions": 15860, "users": 772, "degree": 1, "strength": 149}, {"id": "t5_5rq3lz", "name": "SkincareAddictionLux", "interactions": 9539, "users": 768, "degree": 2, "strength": 101}, {"id": "t5_2tuti", "name": "TuxedoCats", "interactions": 23432, "users": 1498, "degree": 2, "strength": 235}, {"id": "t5_37kq2", "name": "SkincareAddicts", "interactions": 19567, "users": 1410, "degree": 2, "strength": 171}, {"id": "t5_2qnlf", "name": "cat", "interactions": 12191, "users": 568, "degree": 1, "strength": 118}, {"id": "t5_386h6", "name": "watercolor101", "interactions": 3802, "users": 278, "degree": 1, "strength": 93}, {"id": "t5_32c7p", "name": "britishshorthair", "interactions": 7351, "users": 632, "degree": 1, "strength": 44}, {"id": "t5_3iblf", "name": "SupermodelCats", "interactions": 11899, "users": 609, "degree": 1, "strength": 88}, {"id": "t5_2xgqe", "name": "haircoloring", "interactions": 6261, "users": 276, "degree": 1, "strength": 64}, {"id": "t5_5vej89", "name": "OneOrangeBraincell", "interactions": 45257, "users": 2315, "degree": 3, "strength": 341}, {"id": "t5_2yfo0", "name": "jawsurgery", "interactions": 23057, "users": 1876, "degree": 2, "strength": 120}, {"id": "t5_hwe5w", "name": "airplaneears", "interactions": 13335, "users": 700, "degree": 1, "strength": 46}, {"id": "t5_2yjxy", "name": "ArtistLounge", "interactions": 22268, "users": 1430, "degree": 2, "strength": 96}, {"id": "t5_2uqsa", "name": "Siamesecats", "interactions": 10663, "users": 754, "degree": 1, "strength": 49}, {"id": "t5_2wl6d", "name": "DoggyDNA", "interactions": 20109, "users": 1365, "degree": 1, "strength": 127}, {"id": "t5_312u5", "name": "UnusualArt", "interactions": 5196, "users": 285, "degree": 1, "strength": 30}, {"id": "t5_2yw2v", "name": "CatsBeingCats", "interactions": 9850, "users": 427, "degree": 1, "strength": 55}, {"id": "t5_2sorn", "name": "ratemehonestly", "interactions": 4297, "users": 353, "degree": 1, "strength": 34}, {"id": "t5_2tqzv", "name": "hairstylist", "interactions": 11501, "users": 847, "degree": 1, "strength": 30}, {"id": "t5_2sa9a", "name": "FancyFollicles", "interactions": 5037, "users": 390, "degree": 1, "strength": 35}, {"id": "t5_2xl6w", "name": "artbusiness", "interactions": 5543, "users": 409, "degree": 1, "strength": 46}, {"id": "t5_2s82i", "name": "mainecoons", "interactions": 13337, "users": 1102, "degree": 1, "strength": 70}, {"id": "t5_2qwbh", "name": "Rosacea", "interactions": 8878, "users": 963, "degree": 1, "strength": 32}, {"id": "t5_2rddv", "name": "doodles", "interactions": 14070, "users": 643, "degree": 1, "strength": 36}], "edges": [{"source": "t5_2vae5", "target": "t5_2wn4a", "shared_users": 77, "cosine": 0.036376112909513474, "jaccard": 0.012048192771084338}, {"source": "t5_2wn4a", "target": "t5_3cbed", "shared_users": 87, "cosine": 0.01272884405052377, "jaccard": 0.006296135475466783}, {"source": "t5_2wn4a", "target": "t5_prg6z", "shared_users": 68, "cosine": 0.009109957282089097, "jaccard": 0.0044092854363895735}, {"source": "t5_2wn4a", "target": "t5_2qmsf", "shared_users": 175, "cosine": 0.03957040934568675, "jaccard": 0.019557443004023244}, {"source": "t5_2wn4a", "target": "t5_2rkzz", "shared_users": 77, "cosine": 0.01698245629396007, "jaccard": 0.008349598785512904}, {"source": "t5_2wn4a", "target": "t5_7bc4vn", "shared_users": 101, "cosine": 0.01574802867249673, "jaccard": 0.0078777006473754}, {"source": "t5_2wn4a", "target": "t5_35s40", "shared_users": 43, "cosine": 0.013585737869958498, "jaccard": 0.0058108108108108104}, {"source": "t5_2wn4a", "target": "t5_37xo2", "shared_users": 52, "cosine": 0.005260505148811562, "jaccard": 0.0022774055095694827}, {"source": "t5_2wn4a", "target": "t5_2rgjh", "shared_users": 84, "cosine": 0.012352393959373896, "jaccard": 0.0061144271364099575}, {"source": "t5_2wn4a", "target": "t5_2um28", "shared_users": 118, "cosine": 0.0285500686591839, "jaccard": 0.013770568327692845}, {"source": "t5_2wn4a", "target": "t5_2rww2", "shared_users": 65, "cosine": 0.01254938600253824, "jaccard": 0.0062874830721609595}, {"source": "t5_2wn4a", "target": "t5_2rn7d", "shared_users": 84, "cosine": 0.012778490654186828, "jaccard": 0.006361708573159649}, {"source": "t5_2wn4a", "target": "t5_3hjjf", "shared_users": 120, "cosine": 0.01318536313136225, "jaccard": 0.005957108816521049}, {"source": "t5_2wn4a", "target": "t5_2scm4", "shared_users": 73, "cosine": 0.01513400746327411, "jaccard": 0.007523446356796867}, {"source": "t5_2wn4a", "target": "t5_2xgqe", "shared_users": 64, "cosine": 0.05111984150141989, "jaccard": 0.010864029876082159}, {"source": "t5_2wn4a", "target": "t5_2sa9a", "shared_users": 35, "cosine": 0.02351796861689066, "jaccard": 0.00580046403712297}, {"source": "t5_2wn4a", "target": "t5_3bt1s", "shared_users": 63, "cosine": 0.010579695492802084, "jaccard": 0.005311973018549747}, {"source": "t5_2qhta", "target": "t5_2sn56", "shared_users": 375, "cosine": 0.0285642283812268, "jaccard": 0.011402335198248601}, {"source": "t5_2qhta", "target": "t5_3h7cm", "shared_users": 36, "cosine": 0.01072186709536476, "jaccard": 0.0013222654815250128}, {"source": "t5_2qhta", "target": "t5_3n328", "shared_users": 52, "cosine": 0.012819340121893825, "jaccard": 0.001897602452286246}, {"source": "t5_2qhta", "target": "t5_3g77o3", "shared_users": 59, "cosine": 0.014081719898898747, "jaccard": 0.0021503808725443743}, {"source": "t5_2qhta", "target": "t5_prg6z", "shared_users": 86, "cosine": 0.005299493665457918, "jaccard": 0.002351847294008259}, {"source": "t5_2qhta", "target": "t5_2qn3z", "shared_users": 59, "cosine": 0.013505472261398517, "jaccard": 0.002145922746781116}, {"source": "t5_2qhta", "target": "t5_2vgxd", "shared_users": 79, "cosine": 0.014127219486417687, "jaccard": 0.0028287023775422516}, {"source": "t5_2qhta", "target": "t5_31m29", "shared_users": 146, "cosine": 0.025185075396043442, "jaccard": 0.00522398740518105}, {"source": "t5_2qhta", "target": "t5_2ryza", "shared_users": 296, "cosine": 0.028096130931759222, "jaccard": 0.0096476646784655}, {"source": "t5_2qhta", "target": "t5_2y5wf", "shared_users": 58, "cosine": 0.015406486094172068, "jaccard": 0.002123608670181605}, {"source": "t5_2qhta", "target": "t5_3n22p", "shared_users": 30, "cosine": 0.007238087546651091, "jaccard": 0.001092816552528049}, {"source": "t5_2qhta", "target": "t5_2qnh3", "shared_users": 30, "cosine": 0.0037237941938489867, "jaccard": 0.0010263427984946972}, {"source": "t5_2qhta", "target": "t5_3cbed", "shared_users": 89, "cosine": 0.005989467573838998, "jaccard": 0.0025443837731210154}, {"source": "t5_2qhta", "target": "t5_2wnt6", "shared_users": 35, "cosine": 0.010387007008359116, "jaccard": 0.0012853470437017994}, {"source": "t5_2qhta", "target": "t5_3hjjf", "shared_users": 643, "cosine": 0.03249752751856749, "jaccard": 0.015765986661435857}, {"source": "t5_2qhta", "target": "t5_3ccek", "shared_users": 88, "cosine": 0.016158241587303217, "jaccard": 0.0031587637747227107}, {"source": "t5_2qhta", "target": "t5_2xf3z", "shared_users": 30, "cosine": 0.009974677620324824, "jaccard": 0.0011050130759880658}, {"source": "t5_2qhta", "target": "t5_2twpw", "shared_users": 319, "cosine": 0.03346600799979848, "jaccard": 0.010666042530426642}, {"source": "t5_2qhta", "target": "t5_2sx1m", "shared_users": 64, "cosine": 0.008810098849294505, "jaccard": 0.002226551628165878}, {"source": "t5_2qhta", "target": "t5_23e19j", "shared_users": 40, "cosine": 0.011383443058118796, "jaccard": 0.0014672437825544713}, {"source": "t5_2qhta", "target": "t5_7l5bxn", "shared_users": 119, "cosine": 0.022132561197189198, "jaccard": 0.004280575539568346}, {"source": "t5_2qhta", "target": "t5_2st00", "shared_users": 35, "cosine": 0.003949330211012378, "jaccard": 0.0011771432415161604}, {"source": "t5_2qhta", "target": "t5_2vy7f", "shared_users": 29, "cosine": 0.005332118157452578, "jaccard": 0.0010388679921189325}, {"source": "t5_2qhta", "target": "t5_2qnlf", "shared_users": 118, "cosine": 0.030220413571500647, "jaccard": 0.004323611314670966}, {"source": "t5_2qhta", "target": "t5_32c7p", "shared_users": 44, "cosine": 0.010682839445163945, "jaccard": 0.0016040831206707983}, {"source": "t5_2qhta", "target": "t5_3iblf", "shared_users": 88, "cosine": 0.021765396836641134, "jaccard": 0.003216021635054636}, {"source": "t5_2qhta", "target": "t5_5vej89", "shared_users": 204, "cosine": 0.02587898469458171, "jaccard": 0.007045901979069526}, {"source": "t5_2qhta", "target": "t5_2st2l", "shared_users": 99, "cosine": 0.014591357440921413, "jaccard": 0.003478810879190386}, {"source": "t5_2qhta", "target": "t5_hwe5w", "shared_users": 46, "cosine": 0.010612101023485903, "jaccard": 0.0016729706139074776}, {"source": "t5_2qhta", "target": "t5_2suml", "shared_users": 98, "cosine": 0.013751753329664254, "jaccard": 0.0034222656795641847}, {"source": "t5_2qhta", "target": "t5_2uqsa", "shared_users": 49, "cosine": 0.010891883089149582, "jaccard": 0.0017787780883580788}, {"source": "t5_2qhta", "target": "t5_2rn7d", "shared_users": 285, "cosine": 0.019942225919751613, "jaccard": 0.008341626178071767}, {"source": "t5_2qhta", "target": "t5_2tt9j", "shared_users": 116, "cosine": 0.018729856017212686, "jaccard": 0.0041200497247380575}, {"source": "t5_2qhta", "target": "t5_2wp5v", "shared_users": 153, "cosine": 0.02392167089882054, "jaccard": 0.00542303193563251}, {"source": "t5_2qhta", "target": "t5_2yw2v", "shared_users": 55, "cosine": 0.01624580798954141, "jaccard": 0.002021018593371059}, {"source": "t5_2qhta", "target": "t5_2s82i", "shared_users": 70, "cosine": 0.01287063003523036, "jaccard": 0.0025113008538422904}, {"source": "t5_2qhta", "target": "t5_2tuti", "shared_users": 181, "cosine": 0.02854402625572254, "jaccard": 0.006427785077595085}, {"source": "t5_2qhta", "target": "t5_2qmsf", "shared_users": 56, "cosine": 0.005824370849591559, "jaccard": 0.0018524644392987099}, {"source": "t5_2qhta", "target": "t5_2qh1o", "shared_users": 314, "cosine": 0.029454169736826213, "jaccard": 0.010207398738703596}, {"source": "t5_2qhta", "target": "t5_37xo2", "shared_users": 55, "cosine": 0.0025592652169038645, "jaccard": 0.0012501988952787943}, {"source": "t5_2qhta", "target": "t5_2rl0h", "shared_users": 69, "cosine": 0.005883518104559679, "jaccard": 0.002163212841333041}, {"source": "t5_2um28", "target": "t5_2rww2", "shared_users": 97, "cosine": 0.025732256619909532, "jaccard": 0.012704649639816634}, {"source": "t5_2um28", "target": "t5_prg6z", "shared_users": 46, "cosine": 0.008467637895587108, "jaccard": 0.0036013465904642604}, {"source": "t5_2um28", "target": "t5_3hjjf", "shared_users": 54, "cosine": 0.00815270310722424, "jaccard": 0.0030788528422373}, {"source": "t5_2rl0h", "target": "t5_7bx0f3", "shared_users": 69, "cosine": 0.03024110640176154, "jaccard": 0.011365508153516718}, {"source": "t5_2rl0h", "target": "t5_2sgc2", "shared_users": 142, "cosine": 0.03858648353932757, "jaccard": 0.01862295081967213}, {"source": "t5_2rl0h", "target": "t5_37xo2", "shared_users": 66, "cosine": 0.007029095044783188, "jaccard": 0.0029644268774703555}, {"source": "t5_2rl0h", "target": "t5_2qnaq", "shared_users": 36, "cosine": 0.02274277792592863, "jaccard": 0.006455083378160301}, {"source": "t5_2rl0h", "target": "t5_2rn7d", "shared_users": 121, "cosine": 0.019378359911314025, "jaccard": 0.009594037424674913}, {"source": "t5_2rl0h", "target": "t5_3hjjf", "shared_users": 134, "cosine": 0.01550054688605133, "jaccard": 0.006845466155810984}, {"source": "t5_2rl0h", "target": "t5_prg6z", "shared_users": 137, "cosine": 0.019322324382872902, "jaccard": 0.009258007838897148}, {"source": "t5_2rl0h", "target": "t5_3cbed", "shared_users": 75, "cosine": 0.011552137521192229, "jaccard": 0.005649717514124294}, {"source": "t5_2rl0h", "target": "t5_2rddv", "shared_users": 36, "cosine": 0.019833184582456226, "jaccard": 0.006281626243238528}, {"source": "t5_2st00", "target": "t5_2rw7o", "shared_users": 45, "cosine": 0.016290017818422195, "jaccard": 0.008198214611040262}, {"source": "t5_2st00", "target": "t5_2taso", "shared_users": 36, "cosine": 0.014833493731843322, "jaccard": 0.007342443401998776}, {"source": "t5_2rww2", "target": "t5_2qmsf", "shared_users": 82, "cosine": 0.020329529918376103, "jaccard": 0.010140984417511748}, {"source": "t5_2rww2", "target": "t5_2xwgx", "shared_users": 42, "cosine": 0.03010549261261809, "jaccard": 0.008244994110718492}, {"source": "t5_2rww2", "target": "t5_3jayp", "shared_users": 35, "cosine": 0.01693670349852521, "jaccard": 0.006257822277847309}, {"source": "t5_2rww2", "target": "t5_35s40", "shared_users": 36, "cosine": 0.012470913470985546, "jaccard": 0.005579665220086794}, {"source": "t5_2rww2", "target": "t5_2qrwc", "shared_users": 73, "cosine": 0.03094534083551653, "jaccard": 0.01252358895179276}, {"source": "t5_2rww2", "target": "t5_2uols", "shared_users": 60, "cosine": 0.017676261008733075, "jaccard": 0.008447135013374631}, {"source": "t5_2rww2", "target": "t5_2qlac", "shared_users": 58, "cosine": 0.015716315114530633, "jaccard": 0.007683136839316465}, {"source": "t5_2rww2", "target": "t5_2tbbg", "shared_users": 59, "cosine": 0.01053527151798205, "jaccard": 0.005219391365888181}, {"source": "t5_367ex", "target": "t5_2qhhk", "shared_users": 91, "cosine": 0.028287487889543533, "jaccard": 0.0130241877773007}, {"source": "t5_367ex", "target": "t5_319c0", "shared_users": 49, "cosine": 0.01688298654492859, "jaccard": 0.007373965387509405}, {"source": "t5_367ex", "target": "t5_2zw8v", "shared_users": 41, "cosine": 0.01993060438252039, "jaccard": 0.007048306687295857}, {"source": "t5_367ex", "target": "t5_2rw7o", "shared_users": 82, "cosine": 0.022676075486306072, "jaccard": 0.010875331564986738}, {"source": "t5_367ex", "target": "t5_2qjof", "shared_users": 41, "cosine": 0.01099554492034515, "jaccard": 0.005293054479731474}, {"source": "t5_367ex", "target": "t5_2sx1m", "shared_users": 98, "cosine": 0.03121347735153091, "jaccard": 0.014240046498111014}, {"source": "t5_2rgjh", "target": "t5_2rkzz", "shared_users": 88, "cosine": 0.016208251595665996, "jaccard": 0.007537473233404711}, {"source": "t5_2rgjh", "target": "t5_3l18i", "shared_users": 97, "cosine": 0.01940038413140874, "jaccard": 0.00872616048938467}, {"source": "t5_2rgjh", "target": "t5_6s73fd", "shared_users": 93, "cosine": 0.02308538287566764, "jaccard": 0.009260181220750771}, {"source": "t5_2rgjh", "target": "t5_prg6z", "shared_users": 51, "cosine": 0.005705862750096697, "jaccard": 0.0028486845780036863}, {"source": "t5_2rgjh", "target": "t5_3bt1s", "shared_users": 691, "cosine": 0.09690682900667526, "jaccard": 0.05045268691588785}, {"source": "t5_2rgjh", "target": "t5_2scm4", "shared_users": 58, "cosine": 0.010041597147232389, "jaccard": 0.004761122968313906}, {"source": "t5_2rgjh", "target": "t5_2vz7o", "shared_users": 74, "cosine": 0.019727299280764908, "jaccard": 0.007553332652852914}, {"source": "t5_2rgjh", "target": "t5_2w2f5", "shared_users": 51, "cosine": 0.010142549979225481, "jaccard": 0.00455479146199875}, {"source": "t5_2rgjh", "target": "t5_3noa4", "shared_users": 46, "cosine": 0.018011478177659034, "jaccard": 0.005169701056417173}, {"source": "t5_2rgjh", "target": "t5_7bc4vn", "shared_users": 250, "cosine": 0.032552814894629425, "jaccard": 0.0165169133192389}, {"source": "t5_2rgjh", "target": "t5_37xo2", "shared_users": 251, "cosine": 0.021205159565323543, "jaccard": 0.01000079687624512}, {"source": "t5_2rgjh", "target": "t5_2re84", "shared_users": 174, "cosine": 0.03712240104235587, "jaccard": 0.016311990250304678}, {"source": "t5_2rf5w", "target": "t5_2vy7f", "shared_users": 30, "cosine": 0.01902237232731596, "jaccard": 0.009011715229798739}, {"source": "t5_3bt1s", "target": "t5_3l18i", "shared_users": 104, "cosine": 0.023753778605750873, "jaccard": 0.011292073832790446}, {"source": "t5_3bt1s", "target": "t5_3noa4", "shared_users": 49, "cosine": 0.02191030256020507, "jaccard": 0.007004002287021155}, {"source": "t5_3bt1s", "target": "t5_7bc4vn", "shared_users": 160, "cosine": 0.023791909152392383, "jaccard": 0.012005702708786673}, {"source": "t5_3bt1s", "target": "t5_6s73fd", "shared_users": 156, "cosine": 0.044222114203358594, "jaccard": 0.01930454151713897}, {"source": "t5_3bt1s", "target": "t5_2scm4", "shared_users": 47, "cosine": 0.009292518379763845, "jaccard": 0.004565766465902467}, {"source": "t5_3bt1s", "target": "t5_37xo2", "shared_users": 255, "cosine": 0.02460190708544931, "jaccard": 0.01099374865272688}, {"source": "t5_3bt1s", "target": "t5_2vz7o", "shared_users": 57, "cosine": 0.01735287903627946, "jaccard": 0.007201516108654453}, {"source": "t5_3bt1s", "target": "t5_2re84", "shared_users": 166, "cosine": 0.04044414587805087, "jaccard": 0.018915223336371922}, {"source": "t5_3bt1s", "target": "t5_2rkzz", "shared_users": 93, "cosine": 0.01956127758945251, "jaccard": 0.009517961314092724}, {"source": "t5_3l18i", "target": "t5_7bc4vn", "shared_users": 158, "cosine": 0.03350646849587696, "jaccard": 0.015558838010832103}, {"source": "t5_3l18i", "target": "t5_2re84", "shared_users": 49, "cosine": 0.017025736966615926, "jaccard": 0.008567931456548347}, {"source": "t5_2qjof", "target": "t5_2ygor", "shared_users": 51, "cosine": 0.03577200262821592, "jaccard": 0.014761215629522432}, {"source": "t5_2qjof", "target": "t5_v051u", "shared_users": 149, "cosine": 0.10183631680488156, "jaccard": 0.04387514723203769}, {"source": "t5_2sgc2", "target": "t5_prg6z", "shared_users": 60, "cosine": 0.011782732848120541, "jaccard": 0.004841052121994514}, {"source": "t5_2sgc2", "target": "t5_3cbed", "shared_users": 57, "cosine": 0.012224522986853358, "jaccard": 0.005271920088790233}, {"source": "t5_2sgc2", "target": "t5_3hjjf", "shared_users": 74, "cosine": 0.011918728348021036, "jaccard": 0.0043138626559403054}, {"source": "t5_2sgc2", "target": "t5_2rn7d", "shared_users": 59, "cosine": 0.013156477823685966, "jaccard": 0.005788286078681448}, {"source": "t5_2sgc2", "target": "t5_2qirl", "shared_users": 59, "cosine": 0.023054344528751217, "jaccard": 0.011655472145397076}, {"source": "t5_prg6z", "target": "t5_7bc4vn", "shared_users": 55, "cosine": 0.006524493593695018, "jaccard": 0.003235484440261192}, {"source": "t5_prg6z", "target": "t5_3lfiq", "shared_users": 57, "cosine": 0.020071614584022256, "jaccard": 0.005389561270801815}, {"source": "t5_prg6z", "target": "t5_37xo2", "shared_users": 255, "cosine": 0.019626532748797214, "jaccard": 0.009528435841865331}, {"source": "t5_prg6z", "target": "t5_3cbed", "shared_users": 161, "cosine": 0.017921521829993348, "jaccard": 0.009006489147460281}, {"source": "t5_prg6z", "target": "t5_3hjjf", "shared_users": 179, "cosine": 0.014963844152313603, "jaccard": 0.007391501837552133}, {"source": "t5_prg6z", "target": "t5_2rn7d", "shared_users": 149, "cosine": 0.017245104821789134, "jaccard": 0.008627178507324416}, {"source": "t5_2w0u7", "target": "t5_31f0i", "shared_users": 40, "cosine": 0.04423539371933498, "jaccard": 0.017429193899782137}, {"source": "t5_2w0u7", "target": "t5_2tbbg", "shared_users": 77, "cosine": 0.021646014383689804, "jaccard": 0.009093056211620217}, {"source": "t5_2w0u7", "target": "t5_5erdvw", "shared_users": 71, "cosine": 0.07339325590670809, "jaccard": 0.030524505588993982}, {"source": "t5_2qlac", "target": "t5_2qrwc", "shared_users": 45, "cosine": 0.024418419323679035, "jaccard": 0.011205179282868526}, {"source": "t5_2qlac", "target": "t5_2qkya", "shared_users": 41, "cosine": 0.011764292282398841, "jaccard": 0.005811481218993621}, {"source": "t5_2qlac", "target": "t5_2uols", "shared_users": 44, "cosine": 0.016592982499249113, "jaccard": 0.008336491095111784}, {"source": "t5_2qlac", "target": "t5_379gw", "shared_users": 79, "cosine": 0.023176734567835287, "jaccard": 0.011559847819724904}, {"source": "t5_2qlac", "target": "t5_3yqdrv", "shared_users": 42, "cosine": 0.012472829795686298, "jaccard": 0.006200177147918512}, {"source": "t5_2qlac", "target": "t5_2tbbg", "shared_users": 45, "cosine": 0.010285818538261366, "jaccard": 0.004748338081671415}, {"source": "t5_2qrwc", "target": "t5_2uols", "shared_users": 60, "cosine": 0.035397509338340405, "jaccard": 0.01686814731515322}, {"source": "t5_2ihy50", "target": "t5_2tbbg", "shared_users": 97, "cosine": 0.020866273883881164, "jaccard": 0.009900990099009901}, {"source": "t5_2tbbg", "target": "t5_31nsz", "shared_users": 81, "cosine": 0.026215264356800955, "jaccard": 0.010130065032516258}, {"source": "t5_2tbbg", "target": "t5_2ui5x", "shared_users": 42, "cosine": 0.012568543724632784, "jaccard": 0.005073076458509481}, {"source": "t5_2tbbg", "target": "t5_3fwbd", "shared_users": 149, "cosine": 0.04631395576289634, "jaccard": 0.018511616349857124}, {"source": "t5_2tbbg", "target": "t5_5rq3lz", "shared_users": 43, "cosine": 0.019043050154864447, "jaccard": 0.005839217816404128}, {"source": "t5_2tbbg", "target": "t5_379gw", "shared_users": 136, "cosine": 0.02629269181700765, "jaccard": 0.012911801006360961}, {"source": "t5_2tbbg", "target": "t5_37kq2", "shared_users": 120, "cosine": 0.03922115288689506, "jaccard": 0.01513431706394249}, {"source": "t5_2tbbg", "target": "t5_2qse3", "shared_users": 82, "cosine": 0.02971534720705001, "jaccard": 0.010643821391484943}, {"source": "t5_2tbbg", "target": "t5_2qwbh", "shared_users": 32, "cosine": 0.012655680446336018, "jaccard": 0.004227212681638045}, {"source": "t5_2qhhk", "target": "t5_2rw7o", "shared_users": 78, "cosine": 0.03361909068769451, "jaccard": 0.01697866782760122}, {"source": "t5_2st2l", "target": "t5_2suml", "shared_users": 87, "cosine": 0.04829771944242193, "jaccard": 0.02471590909090909}, {"source": "t5_5u5d30", "target": "t5_7bc4vn", "shared_users": 61, "cosine": 0.013822136938745209, "jaccard": 0.006179718366933442}, {"source": "t5_5u5d30", "target": "t5_458lb9", "shared_users": 88, "cosine": 0.038459558577082394, "jaccard": 0.019349164467897976}, {"source": "t5_5u5d30", "target": "t5_37xo2", "shared_users": 42, "cosine": 0.006174672530071359, "jaccard": 0.002115549287261371}, {"source": "t5_2s1th", "target": "t5_7bc4vn", "shared_users": 78, "cosine": 0.016606205600269583, "jaccard": 0.007638820879443737}, {"source": "t5_2s1th", "target": "t5_37xo2", "shared_users": 98, "cosine": 0.0135369606633066, "jaccard": 0.004862558301081671}, {"source": "t5_2s1th", "target": "t5_2s6zw", "shared_users": 107, "cosine": 0.05764843551226346, "jaccard": 0.02628992628992629}, {"source": "t5_7bc4vn", "target": "t5_ruinb", "shared_users": 46, "cosine": 0.014916475737082395, "jaccard": 0.005405405405405406}, {"source": "t5_7bc4vn", "target": "t5_39em5", "shared_users": 45, "cosine": 0.011355954198667762, "jaccard": 0.004804612427930814}, {"source": "t5_7bc4vn", "target": "t5_37xo2", "shared_users": 288, "cosine": 0.02579843051769662, "jaccard": 0.011920036422333512}, {"source": "t5_7bc4vn", "target": "t5_2re84", "shared_users": 84, "cosine": 0.0190019893695123, "jaccard": 0.008521862635690372}, {"source": "t5_7bc4vn", "target": "t5_2vz7o", "shared_users": 90, "cosine": 0.025439665569505394, "jaccard": 0.010133993919603648}, {"source": "t5_7bc4vn", "target": "t5_2rkzz", "shared_users": 175, "cosine": 0.03417625888624306, "jaccard": 0.016373502994011975}, {"source": "t5_7bc4vn", "target": "t5_2scm4", "shared_users": 77, "cosine": 0.014135087479229645, "jaccard": 0.006836544437538844}, {"source": "t5_3cbed", "target": "t5_3hjjf", "shared_users": 1495, "cosine": 0.1364877339289443, "jaccard": 0.07013510977669356}, {"source": "t5_3cbed", "target": "t5_319c0", "shared_users": 49, "cosine": 0.013180961350314555, "jaccard": 0.004971086537486051}, {"source": "t5_3cbed", "target": "t5_37xo2", "shared_users": 82, "cosine": 0.006892543893955914, "jaccard": 0.003234714003944773}, {"source": "t5_3cbed", "target": "t5_2r2ct", "shared_users": 38, "cosine": 0.00946612044479673, "jaccard": 0.003744949246082586}, {"source": "t5_3cbed", "target": "t5_2qm5g", "shared_users": 46, "cosine": 0.021023353204657903, "jaccard": 0.005249942935402876}, {"source": "t5_3cbed", "target": "t5_2rn7d", "shared_users": 957, "cosine": 0.12096334646764095, "jaccard": 0.06432316171528431}, {"source": "t5_3cbed", "target": "t5_3afrc", "shared_users": 114, "cosine": 0.038211744777954824, "jaccard": 0.012399390907113336}, {"source": "t5_28jabm", "target": "t5_2vbb3", "shared_users": 413, "cosine": 0.09915223653894743, "jaccard": 0.05001816640426305}, {"source": "t5_28jabm", "target": "t5_2sda0", "shared_users": 168, "cosine": 0.04028221045411992, "jaccard": 0.01972757162987318}, {"source": "t5_2vbb3", "target": "t5_2sda0", "shared_users": 475, "cosine": 0.08569373602120452, "jaccard": 0.0447648666478183}, {"source": "t5_2vbb3", "target": "t5_2s8y4", "shared_users": 88, "cosine": 0.020008898497206308, "jaccard": 0.009841198836949228}, {"source": "t5_2vbb3", "target": "t5_cqsr2u", "shared_users": 96, "cosine": 0.06325961245733772, "jaccard": 0.01639344262295082}, {"source": "t5_2vbb3", "target": "t5_af2s43", "shared_users": 329, "cosine": 0.13865558923456245, "jaccard": 0.052859897172236506}, {"source": "t5_2vbb3", "target": "t5_2vmr7", "shared_users": 190, "cosine": 0.0656719125957595, "jaccard": 0.027704870224555263}, {"source": "t5_2rkzz", "target": "t5_37xo2", "shared_users": 156, "cosine": 0.019766526262467336, "jaccard": 0.007547169811320755}, {"source": "t5_2rkzz", "target": "t5_2qkya", "shared_users": 35, "cosine": 0.008962270125097595, "jaccard": 0.004488330341113106}, {"source": "t5_319c0", "target": "t5_2wl6d", "shared_users": 127, "cosine": 0.08386538681024297, "jaccard": 0.043522960932145305}, {"source": "t5_29c8x5", "target": "t5_2twpw", "shared_users": 64, "cosine": 0.04964321406743811, "jaccard": 0.016789087093389297}, {"source": "t5_2twpw", "target": "t5_3hjjf", "shared_users": 86, "cosine": 0.012239562603182343, "jaccard": 0.004808767613509282}, {"source": "t5_2sn56", "target": "t5_2ryza", "shared_users": 187, "cosine": 0.0362912990958673, "jaccard": 0.018034525990934518}, {"source": "t5_2sn56", "target": "t5_2uobx", "shared_users": 59, "cosine": 0.031568302305536644, "jaccard": 0.008543295684911672}, {"source": "t5_2sn56", "target": "t5_3hjjf", "shared_users": 77, "cosine": 0.007956758440226756, "jaccard": 0.003679105547326676}, {"source": "t5_2sn56", "target": "t5_2qh6o", "shared_users": 54, "cosine": 0.018260130251378834, "jaccard": 0.0069866735670850045}, {"source": "t5_2sn56", "target": "t5_2sx1m", "shared_users": 79, "cosine": 0.022234839535829668, "jaccard": 0.009508907077515647}, {"source": "t5_7bx0f3", "target": "t5_2qvp9", "shared_users": 42, "cosine": 0.02724503220004376, "jaccard": 0.012677331723513431}, {"source": "t5_7bx0f3", "target": "t5_312u5", "shared_users": 30, "cosine": 0.05575091130255239, "jaccard": 0.023603461841070025}, {"source": "t5_26594g", "target": "t5_2qirl", "shared_users": 83, "cosine": 0.06881900524167309, "jaccard": 0.027833668678739102}, {"source": "t5_2qirl", "target": "t5_2swg6", "shared_users": 114, "cosine": 0.07706795737844797, "jaccard": 0.0351093316907915}, {"source": "t5_2qirl", "target": "t5_2qh7a", "shared_users": 71, "cosine": 0.046274943274846575, "jaccard": 0.02114983616324099}, {"source": "t5_2qirl", "target": "t5_2td8l", "shared_users": 68, "cosine": 0.03953266554949359, "jaccard": 0.018867924528301886}, {"source": "t5_2qirl", "target": "t5_2qvp9", "shared_users": 71, "cosine": 0.029491209669505542, "jaccard": 0.014959966287399916}, {"source": "t5_37xo2", "target": "t5_3hjjf", "shared_users": 65, "cosine": 0.004103176328885127, "jaccard": 0.0020487927882493853}, {"source": "t5_37xo2", "target": "t5_2re84", "shared_users": 58, "cosine": 0.008512694768895776, "jaccard": 0.0029225032752191876}, {"source": "t5_37xo2", "target": "t5_2scm4", "shared_users": 71, "cosine": 0.008456397856476483, "jaccard": 0.0033440090429540316}, {"source": "t5_37xo2", "target": "t5_2vz7o", "shared_users": 66, "cosine": 0.01210408896775128, "jaccard": 0.0034979860080559676}, {"source": "t5_37xo2", "target": "t5_39em5", "shared_users": 134, "cosine": 0.021939928107466936, "jaccard": 0.006964656964656965}, {"source": "t5_37xo2", "target": "t5_2s6zw", "shared_users": 58, "cosine": 0.013147910279378044, "jaccard": 0.0031730401006619616}, {"source": "t5_2qh7a", "target": "t5_2qvp9", "shared_users": 52, "cosine": 0.03488401223066193, "jaccard": 0.01606425702811245}, {"source": "t5_2qvp9", "target": "t5_2rwal", "shared_users": 48, "cosine": 0.02630093160006242, "jaccard": 0.012920592193808884}, {"source": "t5_2qvp9", "target": "t5_2ub51", "shared_users": 95, "cosine": 0.045905457737455954, "jaccard": 0.023312883435582823}, {"source": "t5_2qvp9", "target": "t5_2qncz", "shared_users": 92, "cosine": 0.07919263796283124, "jaccard": 0.032577903682719546}, {"source": "t5_2qvp9", "target": "t5_2qh79", "shared_users": 79, "cosine": 0.06884268224754257, "jaccard": 0.02798441374424371}, {"source": "t5_2rwal", "target": "t5_2qh79", "shared_users": 45, "cosine": 0.05025778240589564, "jaccard": 0.023171987641606592}, {"source": "t5_2rwal", "target": "t5_2vzhu", "shared_users": 56, "cosine": 0.04759922699483035, "jaccard": 0.023931623931623933}, {"source": "t5_2sda0", "target": "t5_2vmr7", "shared_users": 112, "cosine": 0.03866300766229689, "jaccard": 0.016115107913669064}, {"source": "t5_2sda0", "target": "t5_2s8y4", "shared_users": 397, "cosine": 0.09015349439916712, "jaccard": 0.04591187695154389}, {"source": "t5_2sda0", "target": "t5_2y0nv", "shared_users": 38, "cosine": 0.008244249764202363, "jaccard": 0.004068522483940043}, {"source": "t5_2sda0", "target": "t5_3yqdrv", "shared_users": 565, "cosine": 0.12093165127961684, "jaccard": 0.06335501233460417}, {"source": "t5_2qh1o", "target": "t5_2s427", "shared_users": 33, "cosine": 0.020584682249296344, "jaccard": 0.006863560732113145}, {"source": "t5_2qh1o", "target": "t5_3hjjf", "shared_users": 59, "cosine": 0.007507984512252882, "jaccard": 0.00314498933901919}, {"source": "t5_2qh1o", "target": "t5_2suml", "shared_users": 66, "cosine": 0.023318893699159574, "jaccard": 0.01089108910891089}, {"source": "t5_2suml", "target": "t5_snj8v", "shared_users": 48, "cosine": 0.04523995752252733, "jaccard": 0.01968019680196802}, {"source": "t5_2suml", "target": "t5_3n22p", "shared_users": 30, "cosine": 0.027262815323545558, "jaccard": 0.011990407673860911}, {"source": "t5_30sy6", "target": "t5_3epk9", "shared_users": 110, "cosine": 0.12418862487740184, "jaccard": 0.06425233644859812}, {"source": "t5_30sy6", "target": "t5_2r5qg", "shared_users": 51, "cosine": 0.03844068708662826, "jaccard": 0.019325502084122773}, {"source": "t5_30sy6", "target": "t5_31m29", "shared_users": 45, "cosine": 0.03793387368505397, "jaccard": 0.019305019305019305}, {"source": "t5_30sy6", "target": "t5_3afrc", "shared_users": 39, "cosine": 0.03536452433312013, "jaccard": 0.01799723119520074}, {"source": "t5_2qkya", "target": "t5_3oxw9d", "shared_users": 61, "cosine": 0.02795727791747652, "jaccard": 0.011548655812192351}, {"source": "t5_2qkya", "target": "t5_379gw", "shared_users": 86, "cosine": 0.020871333545584105, "jaccard": 0.010543091822974133}, {"source": "t5_2qkya", "target": "t5_2yfo0", "shared_users": 75, "cosine": 0.02667774498693719, "jaccard": 0.012470901230462255}, {"source": "t5_2uols", "target": "t5_3jayp", "shared_users": 43, "cosine": 0.028958651881234917, "jaccard": 0.013030303030303031}, {"source": "t5_2uols", "target": "t5_3yqdrv", "shared_users": 69, "cosine": 0.022278257397768144, "jaccard": 0.010947168015230843}, {"source": "t5_2uols", "target": "t5_30vvl", "shared_users": 129, "cosine": 0.06710849414191104, "jaccard": 0.03372549019607843}, {"source": "t5_ruinb", "target": "t5_2vz7o", "shared_users": 50, "cosine": 0.03319447254910977, "jaccard": 0.01671681711802073}, {"source": "t5_6s73fd", "target": "t5_2re84", "shared_users": 116, "cosine": 0.050024570343546175, "jaccard": 0.0253551912568306}, {"source": "t5_6s73fd", "target": "t5_2qoqt", "shared_users": 53, "cosine": 0.03053137227225483, "jaccard": 0.015353418308227115}, {"source": "t5_6s73fd", "target": "t5_2w2f5", "shared_users": 76, "cosine": 0.03055126101884363, "jaccard": 0.015133412982875348}, {"source": "t5_379gw", "target": "t5_3x4r2p", "shared_users": 45, "cosine": 0.03120578700487044, "jaccard": 0.009997778271495223}, {"source": "t5_379gw", "target": "t5_31nsz", "shared_users": 55, "cosine": 0.022847081104969753, "jaccard": 0.010160724182523555}, {"source": "t5_379gw", "target": "t5_5rq3lz", "shared_users": 58, "cosine": 0.03296817148177836, "jaccard": 0.012236286919831224}, {"source": "t5_379gw", "target": "t5_3fwbd", "shared_users": 43, "cosine": 0.017155085026670024, "jaccard": 0.007753335737468446}, {"source": "t5_2qmsf", "target": "t5_2sgxv", "shared_users": 36, "cosine": 0.0229252678352929, "jaccard": 0.008729388942774006}, {"source": "t5_2qmsf", "target": "t5_2tqzv", "shared_users": 30, "cosine": 0.0175649928831318, "jaccard": 0.0070406007979347575}, {"source": "t5_3hjjf", "target": "t5_2qn3z", "shared_users": 36, "cosine": 0.011179296729225295, "jaccard": 0.00235910878112713}, {"source": "t5_3hjjf", "target": "t5_7j5zwe", "shared_users": 38, "cosine": 0.006932610006878153, "jaccard": 0.002288191726380442}, {"source": "t5_3hjjf", "target": "t5_2wp5v", "shared_users": 91, "cosine": 0.019301705815438195, "jaccard": 0.005681108752653265}, {"source": "t5_3hjjf", "target": "t5_2tt9j", "shared_users": 41, "cosine": 0.008980789675362151, "jaccard": 0.002566831528203844}, {"source": "t5_3hjjf", "target": "t5_3afrc", "shared_users": 73, "cosine": 0.018376212866788325, "jaccard": 0.004681287674746698}, {"source": "t5_3hjjf", "target": "t5_2rn7d", "shared_users": 2060, "cosine": 0.19554657405757792, "jaccard": 0.10231449289758618}, {"source": "t5_3hjjf", "target": "t5_2tuti", "shared_users": 54, "cosine": 0.011552730342910855, "jaccard": 0.003368893879842785}, {"source": "t5_3hjjf", "target": "t5_7l5bxn", "shared_users": 50, "cosine": 0.012615629789169821, "jaccard": 0.003202664616961312}, {"source": "t5_2rn7d", "target": "t5_3afrc", "shared_users": 49, "cosine": 0.0170772783641344, "jaccard": 0.005669983800046285}, {"source": "t5_2ryza", "target": "t5_2sx1m", "shared_users": 80, "cosine": 0.028058243075278596, "jaccard": 0.013286829430327189}, {"source": "t5_2ryza", "target": "t5_2sic2", "shared_users": 35, "cosine": 0.02655862838394402, "jaccard": 0.007743362831858407}, {"source": "t5_2scm4", "target": "t5_2w2f5", "shared_users": 44, "cosine": 0.012336412770973098, "jaccard": 0.006146968426934898}, {"source": "t5_2scm4", "target": "t5_8mnmsd", "shared_users": 223, "cosine": 0.10300513338725568, "jaccard": 0.04444001594260662}, {"source": "t5_2w2f5", "target": "t5_2re83", "shared_users": 49, "cosine": 0.022314108985493672, "jaccard": 0.010631373399869819}, {"source": "t5_2w2f5", "target": "t5_2qoqt", "shared_users": 134, "cosine": 0.06184407533464481, "jaccard": 0.029890698193174213}, {"source": "t5_2w2f5", "target": "t5_71gtbx", "shared_users": 123, "cosine": 0.07883449280137424, "jaccard": 0.03266064790228359}, {"source": "t5_2w2f5", "target": "t5_9jxvcg", "shared_users": 48, "cosine": 0.036630923642748614, "jaccard": 0.013296398891966758}, {"source": "t5_2w2f5", "target": "t5_2vxds", "shared_users": 32, "cosine": 0.027597848605168795, "jaccard": 0.00912721049629207}, {"source": "t5_2rw7o", "target": "t5_2zw8v", "shared_users": 42, "cosine": 0.02830898338691559, "jaccard": 0.012316715542521995}, {"source": "t5_2rw7o", "target": "t5_2taso", "shared_users": 44, "cosine": 0.019203349915054898, "jaccard": 0.009613283810356128}, {"source": "t5_2qoqt", "target": "t5_2re83", "shared_users": 32, "cosine": 0.02088278200314879, "jaccard": 0.010550609957138147}, {"source": "t5_2y0nv", "target": "t5_30vvl", "shared_users": 47, "cosine": 0.019516663623207104, "jaccard": 0.008874622356495469}, {"source": "t5_2y0nv", "target": "t5_2s8y4", "shared_users": 61, "cosine": 0.0166794766663949, "jaccard": 0.008401046687784052}, {"source": "t5_2y0nv", "target": "t5_3yqdrv", "shared_users": 112, "cosine": 0.02886490183786476, "jaccard": 0.014642436919858805}, {"source": "t5_2y0nv", "target": "t5_2t5r0", "shared_users": 40, "cosine": 0.029296082243836792, "jaccard": 0.00935672514619883}, {"source": "t5_2ub51", "target": "t5_2qoaq", "shared_users": 49, "cosine": 0.03562884527100431, "jaccard": 0.017406749555950268}, {"source": "t5_2ub51", "target": "t5_2yjxy", "shared_users": 50, "cosine": 0.030899952616194992, "jaccard": 0.015571473061351603}, {"source": "t5_2wp5v", "target": "t5_5vej89", "shared_users": 67, "cosine": 0.03567030489486708, "jaccard": 0.017762460233297986}, {"source": "t5_2s8y4", "target": "t5_3yqdrv", "shared_users": 567, "cosine": 0.15295357609693874, "jaccard": 0.0826530612244898}, {"source": "t5_31m29", "target": "t5_2v6m5", "shared_users": 58, "cosine": 0.09148993371022016, "jaccard": 0.03828382838283828}, {"source": "t5_32xps", "target": "t5_qp633", "shared_users": 96, "cosine": 0.15287108736377694, "jaccard": 0.08275862068965517}, {"source": "t5_32xps", "target": "t5_2yfo0", "shared_users": 45, "cosine": 0.04162479172046952, "jaccard": 0.018337408312958436}, {"source": "t5_2qoaq", "target": "t5_32v6c", "shared_users": 41, "cosine": 0.044040548126948444, "jaccard": 0.02239213544511196}, {"source": "t5_458lb9", "target": "t5_37fyau", "shared_users": 51, "cosine": 0.06596567527997281, "jaccard": 0.02315024965955515}, {"source": "t5_6r2wpv", "target": "t5_9jxvcg", "shared_users": 51, "cosine": 0.08989719027352835, "jaccard": 0.0470479704797048}, {"source": "t5_2qse3", "target": "t5_2ui5x", "shared_users": 30, "cosine": 0.02159864717222388, "jaccard": 0.010718113612004287}, {"source": "t5_2qnh3", "target": "t5_2sgkq", "shared_users": 30, "cosine": 0.02814130139305609, "jaccard": 0.010496850944716585}, {"source": "t5_2re84", "target": "t5_2sorn", "shared_users": 34, "cosine": 0.03483939395523141, "jaccard": 0.011269472986410341}, {"source": "t5_35s40", "target": "t5_22m7gw", "shared_users": 33, "cosine": 0.03675416404982049, "jaccard": 0.015082266910420476}, {"source": "t5_2tqbr", "target": "t5_3yqdrv", "shared_users": 62, "cosine": 0.020818835958362116, "jaccard": 0.010120796604635978}, {"source": "t5_3yqdrv", "target": "t5_2w8pb", "shared_users": 55, "cosine": 0.03134150413907772, "jaccard": 0.011800042909246944}, {"source": "t5_2r5qg", "target": "t5_2qiy5", "shared_users": 38, "cosine": 0.026009966320305423, "jaccard": 0.013144240747146317}, {"source": "t5_2td8l", "target": "t5_386h6", "shared_users": 93, "cosine": 0.1614203881215515, "jaccard": 0.0674401740391588}, {"source": "t5_3fwbd", "target": "t5_37kq2", "shared_users": 51, "cosine": 0.034398346126015285, "jaccard": 0.017477724468814255}, {"source": "t5_2yjxy", "target": "t5_2xl6w", "shared_users": 46, "cosine": 0.0601489650320445, "jaccard": 0.025655326268823202}]}