{"nodes": [{"id": "t5_2qhe0", "name": "Cricket", "interactions": 355615, "users": 8731, "degree": 27, "strength": 3925}, {"id": "t5_2qkhb", "name": "melbourne", "interactions": 105524, "users": 6937, "degree": 9, "strength": 2407}, {"id": "t5_2hqqj5", "name": "ASX_Bets", "interactions": 28616, "users": 1379, "degree": 2, "strength": 175}, {"id": "t5_2uo3q", "name": "AusFinance", "interactions": 48626, "users": 3685, "degree": 15, "strength": 2179}, {"id": "t5_2g3blu", "name": "CoronavirusDownunder", "interactions": 133408, "users": 4955, "degree": 13, "strength": 2754}, {"id": "t5_2qhma", "name": "newzealand", "interactions": 155013, "users": 8110, "degree": 13, "strength": 3839}, {"id": "t5_2qh8e", "name": "australia", "interactions": 137548, "users": 7929, "degree": 22, "strength": 5315}, {"id": "t5_2snwr", "name": "AustralianPolitics", "interactions": 18010, "users": 781, "degree": 1, "strength": 197}, {"id": "t5_2qkob", "name": "sydney", "interactions": 58517, "users": 4200, "degree": 5, "strength": 1527}, {"id": "t5_2zqu2", "name": "AusLegal", "interactions": 5389, "users": 460, "degree": 1, "strength": 41}, {"id": "t5_2rd5j", "name": "auckland", "interactions": 37370, "users": 3011, "degree": 4, "strength": 1560}, {"id": "t5_38zrx", "name": "PersonalFinanceNZ", "interactions": 13486, "users": 1249, "degree": 2, "strength": 621}, {"id": "t5_340dk", "name": "AskAnAustralian", "interactions": 14118, "users": 847, "degree": 3, "strength": 294}, {"id": "t5_2stjv", "name": "auslaw", "interactions": 6766, "users": 496, "degree": 1, "strength": 32}, {"id": "t5_2qn90", "name": "nrl", "interactions": 16841, "users": 913, "degree": 2, "strength": 212}, {"id": "t5_2r78m", "name": "perth", "interactions": 53440, "users": 3510, "degree": 6, "strength": 1039}, {"id": "t5_2qhoy", "name": "AFL", "interactions": 11644, "users": 871, "degree": 3, "strength": 273}, {"id": "t5_2goljt", "name": "Coronavirus_NZ", "interactions": 11164, "users": 649, "degree": 2, "strength": 326}, {"id": "t5_2r584", "name": "canberra", "interactions": 11207, "users": 1085, "degree": 3, "strength": 243}, {"id": "t5_2qutz", "name": "brisbane", "interactions": 45066, "users": 3188, "degree": 4, "strength": 875}, {"id": "t5_2s6c7", "name": "Aleague", "interactions": 13397, "users": 582, "degree": 2, "strength": 91}, {"id": "t5_39zkf", "name": "fiaustralia", "interactions": 5780, "users": 510, "degree": 1, "strength": 215}, {"id": "t5_w3kny", "name": "diynz", "interactions": 3015, "users": 300, "degree": 1, "strength": 102}, {"id": "t5_2xkkxo", "name": "LockdownSkepticismAU", "interactions": 10314, "users": 374, "degree": 1, "strength": 76}, {"id": "t5_2wtac", "name": "AusProperty", "interactions": 1832, "users": 189, "degree": 1, "strength": 72}, {"id": "t5_2rjoj", "name": "newcastle", "interactions": 10898, "users": 959, "degree": 3, "strength": 219}, {"id": "t5_2r1ca", "name": "Adelaide", "interactions": 48499, "users": 3091, "degree": 5, "strength": 747}, {"id": "t5_2s3eo", "name": "Wellington", "interactions": 12045, "users": 1043, "degree": 1, "strength": 389}, {"id": "t5_2qnjg", "name": "tasmania", "interactions": 3546, "users": 346, "degree": 1, "strength": 48}, {"id": "t5_3bgex", "name": "ausstocks", "interactions": 1264, "users": 111, "degree": 1, "strength": 32}, {"id": "t5_3fzqh", "name": "CricketShitpost", "interactions": 10055, "users": 699, "degree": 1, "strength": 344}, {"id": "t5_2sbpq", "name": "chch", "interactions": 8395, "users": 844, "degree": 1, "strength": 272}, {"id": "t5_zxhx5", "name": "ConservativeKiwi", "interactions": 20189, "users": 636, "degree": 1, "strength": 217}, {"id": "t5_2wxtr", "name": "AusMemes", "interactions": 2868, "users": 183, "degree": 1, "strength": 33}, {"id": "t5_2syt8", "name": "v8supercars", "interactions": 4120, "users": 255, "degree": 2, "strength": 91}], "edges": [{"source": "t5_2qhe0", "target": "t5_2qkhb", "shared_users": 104, "cosine": 0.013363354761978679, "jaccard": 0.006682086867129272}, {"source": "t5_2qhe0", "target": "t5_2qkob", "shared_users": 91, "cosine": 0.015027431362451335, "jaccard": 0.007087227414330218}, {"source": "t5_2qhe0", "target": "t5_2qn90", "shared_users": 148, "cosine": 0.052419676026954735, "jaccard": 0.015585509688289806}, {"source": "t5_2qhe0", "target": "t5_2qhoy", "shared_users": 135, "cosine": 0.048954508752887996, "jaccard": 0.0142600612654484}, {"source": "t5_2qhe0", "target": "t5_2g3blu", "shared_users": 131, "cosine": 0.01991670414493584, "jaccard": 0.00966433050534858}, {"source": "t5_2qhe0", "target": "t5_2s6c7", "shared_users": 50, "cosine": 0.022180764862029283, "jaccard": 0.005397819281010472}, {"source": "t5_2qhe0", "target": "t5_2r78m", "shared_users": 72, "cosine": 0.013006095664890667, "jaccard": 0.00591667351466842}, {"source": "t5_2qhe0", "target": "t5_2r1ca", "shared_users": 60, "cosine": 0.011549674736540453, "jaccard": 0.005101173269852066}, {"source": "t5_2qhe0", "target": "t5_2qh8e", "shared_users": 210, "cosine": 0.02523934567372273, "jaccard": 0.01276595744680851}, {"source": "t5_2qhe0", "target": "t5_3fzqh", "shared_users": 344, "cosine": 0.13924764551487767, "jaccard": 0.037860444640105656}, {"source": "t5_2qhe0", "target": "t5_2syt8", "shared_users": 42, "cosine": 0.028147978204352983, "jaccard": 0.004695885509838999}, {"source": "t5_2qhe0", "target": "t5_2qhma", "shared_users": 127, "cosine": 0.015092504003922322, "jaccard": 0.00759842048582027}, {"source": "t5_2qkhb", "target": "t5_340dk", "shared_users": 67, "cosine": 0.027640586263192417, "jaccard": 0.008682130361539458}, {"source": "t5_2qkhb", "target": "t5_2g3blu", "shared_users": 465, "cosine": 0.07931316416725735, "jaccard": 0.04069309530060383}, {"source": "t5_2qkhb", "target": "t5_2uo3q", "shared_users": 311, "cosine": 0.06151142606047875, "jaccard": 0.030161962952186986}, {"source": "t5_2qkhb", "target": "t5_2qhoy", "shared_users": 71, "cosine": 0.02888440487898188, "jaccard": 0.00917668346904485}, {"source": "t5_2qkhb", "target": "t5_2qh8e", "shared_users": 674, "cosine": 0.09087927219886364, "jaccard": 0.04749154453213078}, {"source": "t5_2hqqj5", "target": "t5_2uo3q", "shared_users": 121, "cosine": 0.053676537252847066, "jaccard": 0.024479061298806393}, {"source": "t5_2hqqj5", "target": "t5_2qh8e", "shared_users": 54, "cosine": 0.016330610394656893, "jaccard": 0.005835314458612492}, {"source": "t5_2uo3q", "target": "t5_2g3blu", "shared_users": 197, "cosine": 0.04610262464100769, "jaccard": 0.023332938528958902}, {"source": "t5_2uo3q", "target": "t5_2zqu2", "shared_users": 41, "cosine": 0.031490981354542966, "jaccard": 0.009990253411306042}, {"source": "t5_2uo3q", "target": "t5_2stjv", "shared_users": 32, "cosine": 0.02366957140129136, "jaccard": 0.007712701855868884}, {"source": "t5_2uo3q", "target": "t5_39zkf", "shared_users": 215, "cosine": 0.1568319801155478, "jaccard": 0.05402010050251256}, {"source": "t5_2uo3q", "target": "t5_2qh8e", "shared_users": 332, "cosine": 0.0614200447713902, "jaccard": 0.02942740648821131}, {"source": "t5_2uo3q", "target": "t5_2r584", "shared_users": 57, "cosine": 0.02850632554279758, "jaccard": 0.0120942075111394}, {"source": "t5_2uo3q", "target": "t5_2wtac", "shared_users": 72, "cosine": 0.08627457890764245, "jaccard": 0.01893740136770121}, {"source": "t5_2uo3q", "target": "t5_2qutz", "shared_users": 140, "cosine": 0.040846056450424294, "jaccard": 0.020793108569731173}, {"source": "t5_2uo3q", "target": "t5_2qkob", "shared_users": 241, "cosine": 0.0612595287053979, "jaccard": 0.0315279958137101}, {"source": "t5_2uo3q", "target": "t5_3bgex", "shared_users": 32, "cosine": 0.05003452058051427, "jaccard": 0.008501594048884165}, {"source": "t5_2uo3q", "target": "t5_2r1ca", "shared_users": 74, "cosine": 0.02192620504317958, "jaccard": 0.01104148015517756}, {"source": "t5_2uo3q", "target": "t5_2r78m", "shared_users": 127, "cosine": 0.03531273998429689, "jaccard": 0.017968307866440294}, {"source": "t5_2g3blu", "target": "t5_2qh8e", "shared_users": 594, "cosine": 0.09476662339031201, "jaccard": 0.0483319772172498}, {"source": "t5_2g3blu", "target": "t5_2xkkxo", "shared_users": 76, "cosine": 0.05582850030669268, "jaccard": 0.014467923091566724}, {"source": "t5_2g3blu", "target": "t5_2rjoj", "shared_users": 66, "cosine": 0.030276997330206307, "jaccard": 0.011285909712722298}, {"source": "t5_2g3blu", "target": "t5_2r78m", "shared_users": 139, "cosine": 0.03333031457606325, "jaccard": 0.016694691328368965}, {"source": "t5_2g3blu", "target": "t5_2qutz", "shared_users": 188, "cosine": 0.047301712431814295, "jaccard": 0.023632935260842237}, {"source": "t5_2g3blu", "target": "t5_2r1ca", "shared_users": 145, "cosine": 0.0370507215636499, "jaccard": 0.018352107328186304}, {"source": "t5_2g3blu", "target": "t5_2qkob", "shared_users": 358, "cosine": 0.07847594462001495, "jaccard": 0.04069569171308401}, {"source": "t5_2qhma", "target": "t5_2rd5j", "shared_users": 1078, "cosine": 0.21814886411463863, "jaccard": 0.10733844468784227}, {"source": "t5_2qhma", "target": "t5_2goljt", "shared_users": 205, "cosine": 0.08935545807645516, "jaccard": 0.023965396305821837}, {"source": "t5_2qhma", "target": "t5_w3kny", "shared_users": 102, "cosine": 0.06539267710900144, "jaccard": 0.01227732306210881}, {"source": "t5_2qhma", "target": "t5_2s3eo", "shared_users": 389, "cosine": 0.1337509945378484, "jaccard": 0.04438612505705158}, {"source": "t5_2qhma", "target": "t5_38zrx", "shared_users": 430, "cosine": 0.13510667600797163, "jaccard": 0.04815768843095532}, {"source": "t5_2qhma", "target": "t5_2sbpq", "shared_users": 272, "cosine": 0.10396502291257531, "jaccard": 0.0313291868233126}, {"source": "t5_2qhma", "target": "t5_zxhx5", "shared_users": 217, "cosine": 0.09554781256177017, "jaccard": 0.02544260757415875}, {"source": "t5_2qh8e", "target": "t5_2snwr", "shared_users": 197, "cosine": 0.07916468723638176, "jaccard": 0.023141078350757665}, {"source": "t5_2qh8e", "target": "t5_2qkob", "shared_users": 583, "cosine": 0.10102635885561603, "jaccard": 0.050493677464056815}, {"source": "t5_2qh8e", "target": "t5_340dk", "shared_users": 78, "cosine": 0.030098419338640242, "jaccard": 0.008967578753736492}, {"source": "t5_2qh8e", "target": "t5_2r78m", "shared_users": 340, "cosine": 0.06444899506096183, "jaccard": 0.03063339039553113}, {"source": "t5_2qh8e", "target": "t5_2qutz", "shared_users": 352, "cosine": 0.070012292444963, "jaccard": 0.03269856014862982}, {"source": "t5_2qh8e", "target": "t5_2r584", "shared_users": 120, "cosine": 0.040912608308353034, "jaccard": 0.013492241960872498}, {"source": "t5_2qh8e", "target": "t5_2qhoy", "shared_users": 67, "cosine": 0.025495088054873143, "jaccard": 0.00767204855147143}, {"source": "t5_2qh8e", "target": "t5_2rjoj", "shared_users": 97, "cosine": 0.0351765482760202, "jaccard": 0.011034012057786372}, {"source": "t5_2qh8e", "target": "t5_2qnjg", "shared_users": 48, "cosine": 0.02897970625535255, "jaccard": 0.005834447550747538}, {"source": "t5_2qh8e", "target": "t5_2wxtr", "shared_users": 33, "cosine": 0.027395497152570388, "jaccard": 0.004084663943557371}, {"source": "t5_2qh8e", "target": "t5_2r1ca", "shared_users": 287, "cosine": 0.05797265431506087, "jaccard": 0.026739960868349948}, {"source": "t5_2qh8e", "target": "t5_2qn90", "shared_users": 64, "cosine": 0.023786764687071214, "jaccard": 0.007290954659375712}, {"source": "t5_2rd5j", "target": "t5_38zrx", "shared_users": 191, "cosine": 0.09849105065196326, "jaccard": 0.04694028016711723}, {"source": "t5_2rd5j", "target": "t5_2goljt", "shared_users": 121, "cosine": 0.08655808591017085, "jaccard": 0.034190449279457476}]}