{"nodes": [{"id": "t5_2tjtv", "name": "budgies", "interactions": 15171, "users": 1168, "degree": 2, "strength": 160}, {"id": "t5_2uqu9", "name": "cockatiel", "interactions": 11703, "users": 938, "degree": 2, "strength": 172}, {"id": "t5_2qhyf", "name": "parrots", "interactions": 21597, "users": 1583, "degree": 4, "strength": 374}, {"id": "t5_2uvez", "name": "Conures", "interactions": 4180, "users": 366, "degree": 1, "strength": 80}], "edges": [{"source": "t5_2tjtv", "target": "t5_2uqu9", "shared_users": 64, "cosine": 0.061144462752018146, "jaccard": 0.031341821743388835}, {"source": "t5_2tjtv", "target": "t5_2qhyf", "shared_users": 96, "cosine": 0.07060075643477497, "jaccard": 0.03615819209039548}, {"source": "t5_2uqu9", "target": "t5_2qhyf", "shared_users": 108, "cosine": 0.0886302305191686, "jaccard": 0.04475756319933692}, {"source": "t5_2qhyf", "target": "t5_2uvez", "shared_users": 80, "cosine": 0.10510151756372134, "jaccard": 0.042803638309256285}]}