{"nodes": [{"id": "t5_2qzyn", "name": "knives", "interactions": 34940, "users": 2439, "degree": 4, "strength": 817}, {"id": "t5_2ulfn", "name": "knifeclub", "interactions": 22801, "users": 1625, "degree": 3, "strength": 864}, {"id": "t5_2tgpv", "name": "Knife_Swap", "interactions": 39207, "users": 2126, "degree": 5, "strength": 760}, {"id": "t5_3q5big", "name": "bladesInStock", "interactions": 1131, "users": 98, "degree": 1, "strength": 38}, {"id": "t5_2qjmy", "name": "flashlight", "interactions": 42482, "users": 1704, "degree": 2, "strength": 231}, {"id": "t5_3ugk08", "name": "Hanklights", "interactions": 2854, "users": 190, "degree": 1, "strength": 150}, {"id": "t5_2reni", "name": "EDC", "interactions": 28772, "users": 2007, "degree": 5, "strength": 524}, {"id": "t5_2uuu7", "name": "EDCexchange", "interactions": 3662, "users": 310, "degree": 1, "strength": 149}], "edges": [{"source": "t5_2qzyn", "target": "t5_2ulfn", "shared_users": 373, "cosine": 0.18735972875662615, "jaccard": 0.10105662422107829}, {"source": "t5_2qzyn", "target": "t5_2tgpv", "shared_users": 163, "cosine": 0.07158138121328327, "jaccard": 0.03702862335302135}, {"source": "t5_2qzyn", "target": "t5_2reni", "shared_users": 171, "cosine": 0.07728879280608843, "jaccard": 0.04}, {"source": "t5_2ulfn", "target": "t5_2reni", "shared_users": 140, "cosine": 0.07752248162770088, "jaccard": 0.04009163802978236}, {"source": "t5_2ulfn", "target": "t5_2tgpv", "shared_users": 351, "cosine": 0.1888420923469043, "jaccard": 0.10323529411764706}, {"source": "t5_2tgpv", "target": "t5_3q5big", "shared_users": 38, "cosine": 0.08325089836073674, "jaccard": 0.01738334858188472}, {"source": "t5_2tgpv", "target": "t5_2uuu7", "shared_users": 149, "cosine": 0.18353706876960596, "jaccard": 0.06515085264538698}, {"source": "t5_2tgpv", "target": "t5_2reni", "shared_users": 59, "cosine": 0.028562531429744357, "jaccard": 0.014482081492390771}, {"source": "t5_2qjmy", "target": "t5_3ugk08", "shared_users": 150, "cosine": 0.26362079376607644, "jaccard": 0.0860091743119266}, {"source": "t5_2qjmy", "target": "t5_2reni", "shared_users": 81, "cosine": 0.043800244762940546, "jaccard": 0.02231404958677686}]}