{"nodes": [{"id": "t5_3lgkx", "name": "pickoneceleb", "interactions": 20486, "users": 592, "degree": 4, "strength": 348}, {"id": "t5_3ovv9", "name": "CelebAssPussyMouth", "interactions": 8870, "users": 340, "degree": 1, "strength": 135}, {"id": "t5_3ccfx", "name": "TrueFMK", "interactions": 57231, "users": 1053, "degree": 4, "strength": 411}, {"id": "t5_3kfxz", "name": "Pickonepornstar", "interactions": 29517, "users": 801, "degree": 2, "strength": 105}, {"id": "t5_305tg", "name": "Ifyouhadtopickone", "interactions": 45086, "users": 1115, "degree": 3, "strength": 410}, {"id": "t5_38p03", "name": "IRLgirls", "interactions": 30676, "users": 928, "degree": 3, "strength": 143}, {"id": "t5_yo6ki", "name": "CelebBattles", "interactions": 28437, "users": 733, "degree": 1, "strength": 64}, {"id": "t5_33mbt", "name": "WhichOneWouldYouPick", "interactions": 13772, "users": 419, "degree": 3, "strength": 201}, {"id": "t5_2opar5", "name": "WhatWouldYouDoWithHer", "interactions": 3860, "users": 309, "degree": 1, "strength": 26}, {"id": "t5_2o8nq3", "name": "CelebWouldYouRather", "interactions": 4655, "users": 197, "degree": 1, "strength": 84}], "edges": [{"source": "t5_3lgkx", "target": "t5_3ovv9", "shared_users": 135, "cosine": 0.30090780771531694, "jaccard": 0.16938519447929737}, {"source": "t5_3lgkx", "target": "t5_yo6ki", "shared_users": 64, "cosine": 0.09715544231405669, "jaccard": 0.05075337034099921}, {"source": "t5_3lgkx", "target": "t5_3kfxz", "shared_users": 65, "cosine": 0.09439222976022191, "jaccard": 0.04894578313253012}, {"source": "t5_3lgkx", "target": "t5_2o8nq3", "shared_users": 84, "cosine": 0.24597180019663678, "jaccard": 0.11914893617021277}, {"source": "t5_3ccfx", "target": "t5_3kfxz", "shared_users": 40, "cosine": 0.043554150521322575, "jaccard": 0.022050716648291068}, {"source": "t5_3ccfx", "target": "t5_38p03", "shared_users": 54, "cosine": 0.05462677805469223, "jaccard": 0.02802283341982356}, {"source": "t5_3ccfx", "target": "t5_33mbt", "shared_users": 66, "cosine": 0.09936255227276443, "jaccard": 0.04694167852062589}, {"source": "t5_3ccfx", "target": "t5_305tg", "shared_users": 251, "cosine": 0.23164455819705856, "jaccard": 0.1309337506520605}, {"source": "t5_305tg", "target": "t5_38p03", "shared_users": 50, "cosine": 0.04915396801395521, "jaccard": 0.025087807325639738}, {"source": "t5_305tg", "target": "t5_33mbt", "shared_users": 109, "cosine": 0.15947112307832217, "jaccard": 0.07649122807017544}, {"source": "t5_33mbt", "target": "t5_2opar5", "shared_users": 26, "cosine": 0.07225819300768242, "jaccard": 0.037037037037037035}]}